{
    "version": "5.2.0",
    "flags": {},
    "shapes": [
        {
            "label": "bean",
            "points": [
                [
                    1091.2997453056087,
                    268.34019275978204
                ],
                [
                    1103.3124760679884,
                    275.4391563475954
                ],
                [
                    1111.8833284066127,
                    284.78193250586486
                ],
                [
                    1114.3057866392012,
                    291.34890912185205
                ],
                [
                    1115.9377942247218,
                    298.52977150712377
                ],
                [
                    1114.6595357011076,
                    305.49291177174297
                ],
                [
                    1111.8216133863953,
                    312.0479051597889
                ],
                [
                    1106.0256389102665,
                    316.2565516328869
                ],
                [
                    1098.8120293678853,
                    319.2833689777873
                ],
                [
                    1090.8159324068515,
                    319.405882072111
                ],
                [
                    1083.4264437370691,
                    314.9209243395833
                ],
                [
                    1079.0945609474747,
                    315.2804681006637
                ],
                [
                    1071.0161661564996,
                    313.02800321111545
                ],
                [
                    1067.0931136526133,
                    310.94332362253454
                ],
                [
                    1061.1478085983274,
                    311.40473822764216
                ],
                [
                    1054.0669351203776,
                    310.01650670626873
                ],
                [
                    1048.5516978548376,
                    306.3977795465727
                ],
                [
                    1042.8293899233395,
                    301.3009332494173
                ],
                [
                    1040.2151261065196,
                    294.25856159572436
                ],
                [
                    1041.1635319352636,
                    285.8346135350932
                ],
                [
                    1043.2322411059456,
                    278.25758750118945
                ],
                [
                    1046.9966703712603,
                    272.9536686071305
                ],
                [
                    1052.7216304849662,
                    269.1318632598447
                ],
                [
                    1059.2868181051256,
                    265.9452494326045
                ],
                [
                    1064.5856920442934,
                    264.44449084019175
                ],
                [
                    1071.179419020801,
                    264.142872717424
                ],
                [
                    1078.8934493392464,
                    264.68817662138366
                ],
                [
                    1084.9230430305777,
                    265.72219249518275
                ]
            ],
            "group_id": null,
            "description": "",
            "shape_type": "polygon",
            "flags": {}
        },
        {
            "label": "bean",
            "points": [
                [
                    787.455249105324,
                    583.4513147263166
                ],
                [
                    779.9316785835006,
                    572.8382396126201
                ],
                [
                    776.1754892643448,
                    561.623637876954
                ],
                [
                    776.5931584126029,
                    555.1108296402857
                ],
                [
                    777.9131734255566,
                    548.3759406508565
                ],
                [
                    781.6218322840751,
                    542.9332441302029
                ],
                [
                    786.500793635693,
                    538.4312280529368
                ],
                [
                    793.006971865275,
                    537.0520166168186
                ],
                [
                    800.2713793814542,
                    537.2182296819383
                ],
                [
                    807.1058354240906,
                    540.1549310038477
                ],
                [
                    811.6893688372539,
                    546.7840079502027
                ],
                [
                    815.5023906385352,
                    548.1253404154411
                ],
                [
                    821.5119008479166,
                    553.1155390214539
                ],
                [
                    824.0569435968647,
                    556.3825462161091
                ],
                [
                    829.2780639273235,
                    558.2507445399442
                ],
                [
                    834.7663414659349,
                    562.1257132283307
                ],
                [
                    838.0850935077684,
                    567.3044282304924
                ],
                [
                    841.022732355676,
                    573.8204539030414
                ],
                [
                    840.5887837808789,
                    580.8109880018437
                ],
                [
                    836.6097700332042,
                    587.6229508315564
                ],
                [
                    831.99876530999,
                    593.287728104971
                ],
                [
                    826.8046078908533,
                    596.3721422356856
                ],
                [
                    820.5044662645223,
                    597.4489816428786
                ],
                [
                    813.7303314065367,
                    597.6654318828482
                ],
                [
                    808.6664093997119,
                    596.92803911649
                ],
                [
                    802.9550164110595,
                    594.6771774875655
                ],
                [
                    796.6116324468676,
                    591.279130302343
                ],
                [
                    791.8823836151041,
                    588.1055769467921
                ]
            ],
            "group_id": null,
            "description": "",
            "shape_type": "polygon",
            "flags": {}
        },
        {
            "label": "bean",
            "points": [
                [
                    811.6312199422028,
                    1141.8721464828764
                ],
                [
                    818.6701573181534,
                    1140.0276746917232
                ],
                [
                    824.6235193434895,
                    1136.7352991776988
                ],
                [
                    828.992620339636,
                    1134.650936682217
                ],
                [
                    831.047176118988,
                    1135.0771333192686
                ],
                [
                    834.2364104416946,
                    1132.4010336267095
                ],
                [
                    839.4387760150987,
                    1130.6712778821495
                ],
                [
                    844.9828182192886,
                    1130.8795140306738
                ],
                [
                    849.4521464063982,
                    1132.7814956947104
                ],
                [
                    853.684950619082,
                    1135.0309681782526
                ],
                [
                    857.2217974407117,
                    1139.1353710640901
                ],
                [
                    859.4359640053185,
                    1145.0968821888441
                ],
                [
                    859.9056778234977,
                    1149.6886129867205
                ],
                [
                    857.6891875309595,
                    1155.5571864310957
                ],
                [
                    855.3261200534073,
                    1159.6604244738292
                ],
                [
                    850.708471885335,
                    1164.8656708349974
                ],
                [
                    841.387143822434,
                    1169.1447561993116
                ],
                [
                    827.5757753080964,
                    1171.781933555063
                ],
                [
                    818.2577813758679,
                    1170.7743064824892
                ],
                [
                    811.7845919368709,
                    1167.481779118878
                ],
                [
                    805.9316085637225,
                    1162.302084375615
                ],
                [
                    803.1664704583518,
                    1156.374988064839
                ],
                [
                    802.9654351444426,
                    1151.3598208880844
                ],
                [
                    804.6832397584054,
                    1148.1471641851233
                ],
                [
                    807.8703018144053,
                    1144.8427346448875
                ]
            ],
            "group_id": null,
            "description": "",
            "shape_type": "polygon",
            "flags": {}
        },
        {
            "label": "bean",
            "points": [
                [
                    327.59121537371806,
                    974.2949856383544
                ],
                [
                    316.20166830345056,
                    976.2223263973967
                ],
                [
                    305.80519669343755,
                    974.8613222299992
                ],
                [
                    300.7830194027027,
                    971.9653215679884
                ],
                [
                    295.9365922626246,
                    968.2510781294579
                ],
                [
                    293.0522793199246,
                    963.1091430936277
                ],
                [
                    291.37418070869126,
                    957.3885068777402
                ],
                [
                    292.81818736173057,
                    951.5759395849001
                ],
                [
                    295.7888875620921,
                    945.7559972270949
                ],
                [
                    300.79740449178735,
                    941.3723689124163
                ],
                [
                    307.86623305587256,
                    940.2623353942472
                ],
                [
                    310.4240075112344,
                    937.6999903221592
                ],
                [
                    316.7451540261949,
                    934.7911106015107
                ],
                [
                    320.34068538830877,
                    934.0122379115408
                ],
                [
                    323.86811530802413,
                    930.5160345650078
                ],
                [
                    329.0976805621035,
                    927.5914691787825
                ],
                [
                    334.517581418724,
                    926.9365225873494
                ],
                [
                    340.8533133855688,
                    927.1155044380127
                ],
                [
                    346.2494858826734,
                    930.212300300367
                ],
                [
                    350.1183481052261,
                    936.1109828312716
                ],
                [
                    352.82691089726933,
                    942.0711606436214
                ],
                [
                    353.2531886396938,
                    947.4904481363861
                ],
                [
                    351.64894237872664,
                    953.0173523716801
                ],
                [
                    349.1744715448774,
                    958.5903780680579
                ],
                [
                    346.60878763634366,
                    962.4033039580751
                ],
                [
                    342.585128350116,
                    966.1464239660354
                ],
                [
                    337.4011696333789,
                    969.9510392554411
                ],
                [
                    333.0266267730675,
                    972.5361332128556
                ]
            ],
            "group_id": null,
            "description": "",
            "shape_type": "polygon",
            "flags": {}
        },
        {
            "label": "bean",
            "points": [
                [
                    905.2419880394257,
                    81.75787590681716
                ],
                [
                    909.6187241687708,
                    84.57049467660113
                ],
                [
                    914.2203915295925,
                    86.09798521633873
                ],
                [
                    917.4250987807504,
                    87.38208758143425
                ],
                [
                    918.2015248032344,
                    88.67707487256256
                ],
                [
                    921.1406074429736,
                    89.04698407857154
                ],
                [
                    924.565791264373,
                    90.94561486225916
                ],
                [
                    927.1501666719538,
                    93.97717932697054
                ],
                [
                    928.3327228214308,
                    97.27328629941906
                ],
                [
                    929.2198927380417,
                    100.61519525766747
                ],
                [
                    928.8054600193859,
                    104.50097782301306
                ],
                [
                    926.7839156485124,
                    108.60057137975491
                ],
                [
                    924.6267249105045,
                    111.10530773188387
                ],
                [
                    920.5016426780657,
                    112.81826311771295
                ],
                [
                    917.2224302514879,
                    113.58621712326865
                ],
                [
                    912.2757739553878,
                    113.704520477475
                ],
                [
                    905.5258251790283,
                    110.88245299258944
                ],
                [
                    897.44815783278,
                    104.88114567853052
                ],
                [
                    893.4461722601608,
                    99.46273786991618
                ],
                [
                    892.0127711881875,
                    94.42450867437313
                ],
                [
                    891.8609294269133,
                    88.78653965186089
                ],
                [
                    893.5970081054032,
                    84.41274969929012
                ],
                [
                    896.104653657937,
                    81.84187772022688
                ],
                [
                    898.6078445492357,
                    81.1706623898021
                ],
                [
                    901.872277286891,
                    81.2306374482544
                ]
            ],
            "group_id": null,
            "description": "",
            "shape_type": "polygon",
            "flags": {}
        },
        {
            "label": "bean",
            "points": [
                [
                    788.7298872215314,
                    713.3464276799181
                ],
                [
                    790.2741863716276,
                    705.6285102241782
                ],
                [
                    793.615894719674,
                    699.3376766347031
                ],
                [
                    796.6162466544505,
                    696.8398259535879
                ],
                [
                    800.0810022884997,
                    694.6516422686817
                ],
                [
                    803.9581407445045,
                    694.0578598930911
                ],
                [
                    807.9036695214725,
                    694.3719800677499
                ],
                [
                    811.1556646623552,
                    696.6962659600247
                ],
                [
                    814.0452569624227,
                    699.994430222059
                ],
                [
                    815.5556691163695,
                    704.2429965211996
                ],
                [
                    814.5438663907358,
                    709.0122356935944
                ],
                [
                    815.5156382945731,
                    711.2601478522209
                ],
                [
                    815.7973843002493,
                    715.9880764848966
                ],
                [
                    815.4154018736368,
                    718.4657150646706
                ],
                [
                    816.7323355244413,
                    721.5567429011741
                ],
                [
                    817.2861759722223,
                    725.593416986233
                ],
                [
                    816.3889382149952,
                    729.2027398017153
                ],
                [
                    814.7552023163904,
                    733.1936501686055
                ],
                [
                    811.5406230466995,
                    735.8811056782868
                ],
                [
                    806.9582584948619,
                    736.9188845833821
                ],
                [
                    802.6167163395844,
                    737.2029999627638
                ],
                [
                    799.1586785856106,
                    736.1646373307331
                ],
                [
                    796.122080025617,
                    733.8073635287031
                ],
                [
                    793.2660982630438,
                    730.884842082388
                ],
                [
                    791.5218791883852,
                    728.329640821828
                ],
                [
                    790.1713350000865,
                    724.8629701696053
                ],
                [
                    789.061613208348,
                    720.6426359916688
                ],
                [
                    788.5124497444659,
                    717.2324295818545
                ]
            ],
            "group_id": null,
            "description": "",
            "shape_type": "polygon",
            "flags": {}
        },
        {
            "label": "bean",
            "points": [
                [
                    1012.3812290436227,
                    995.8358318443845
                ],
                [
                    1013.7594366079477,
                    983.3628343324535
                ],
                [
                    1012.1631539624293,
                    971.7452930852303
                ],
                [
                    1011.5207703903154,
                    963.4239526338008
                ],
                [
                    1013.4608745153954,
                    960.3780365179199
                ],
                [
                    1011.151145484711,
                    953.5919169799705
                ],
                [
                    1011.5853823468569,
                    944.1473172188639
                ],
                [
                    1015.3190308060771,
                    935.3474453764165
                ],
                [
                    1021.0936313171057,
                    929.3226908972396
                ],
                [
                    1027.277117741439,
                    923.8931049491935
                ],
                [
                    1035.9909291422446,
                    920.7280639509281
                ],
                [
                    1046.8539997239354,
                    920.8382017103886
                ],
                [
                    1054.462866399844,
                    922.9130403521888
                ],
                [
                    1062.45924972785,
                    930.1011184402772
                ],
                [
                    1067.5511973132268,
                    936.4367359712993
                ],
                [
                    1073.016751491842,
                    947.0826917790718
                ],
                [
                    1074.119679525063,
                    964.7325028168646
                ],
                [
                    1069.8499379311309,
                    988.6007862801964
                ],
                [
                    1062.5262274618342,
                    1002.9854216139273
                ],
                [
                    1053.3051513898727,
                    1011.3798312332243
                ],
                [
                    1041.4558757565064,
                    1017.6118103854385
                ],
                [
                    1030.3096139641618,
                    1018.4101919512252
                ],
                [
                    1022.190509275301,
                    1015.6415739686076
                ],
                [
                    1018.1225152305431,
                    1010.8942404116052
                ],
                [
                    1014.8096977475284,
                    1003.7241886539432
                ]
            ],
            "group_id": null,
            "description": "",
            "shape_type": "polygon",
            "flags": {}
        },
        {
            "label": "bean",
            "points": [
                [
                    376.1187081401832,
                    554.8161314370973
                ],
                [
                    378.8703684439909,
                    541.2432421183823
                ],
                [
                    384.82468513687354,
                    530.1800520127537
                ],
                [
                    390.17076676611185,
                    525.7872801252753
                ],
                [
                    396.3443313504176,
                    521.9390950242334
                ],
                [
                    403.25268714475345,
                    520.8948570533671
                ],
                [
                    410.28290205644197,
                    521.4472752915602
                ],
                [
                    416.077366125651,
                    525.5348125503883
                ],
                [
                    421.2260942239532,
                    531.3350324594832
                ],
                [
                    423.9173740618947,
                    538.8066490545235
                ],
                [
                    422.11452556894756,
                    547.193931737011
                ],
                [
                    423.8460464157849,
                    551.1471565676989
                ],
                [
                    424.3480665713532,
                    559.4617896803355
                ],
                [
                    423.6674433384801,
                    563.8190161482138
                ],
                [
                    426.01397966173164,
                    569.254961653789
                ],
                [
                    427.0008226414143,
                    576.3539402171684
                ],
                [
                    425.4021080921732,
                    582.7013699961201
                ],
                [
                    422.4910877637502,
                    589.7198675378924
                ],
                [
                    416.76329197411894,
                    594.4460823997458
                ],
                [
                    408.5983514999356,
                    596.2711418535341
                ],
                [
                    400.8625127505323,
                    596.7707930379638
                ],
                [
                    394.7009182070879,
                    594.9447070299098
                ],
                [
                    389.2902516820086,
                    590.7991565504781
                ],
                [
                    384.20141145051434,
                    585.6595498690273
                ],
                [
                    381.09353019021364,
                    581.1659200659733
                ],
                [
                    378.68710600015413,
                    575.0693613327542
                ],
                [
                    376.7097835348747,
                    567.6473943301762
                ],
                [
                    375.73127409013927,
                    561.650134781882
                ]
            ],
            "group_id": null,
            "description": "",
            "shape_type": "polygon",
            "flags": {}
        },
        {
            "label": "bean",
            "points": [
                [
                    114.804156936422,
                    858.7914772349077
                ],
                [
                    112.46330074664196,
                    849.0974559405859
                ],
                [
                    108.1275446644344,
                    840.8571391327819
                ],
                [
                    105.39691238420268,
                    834.8175908212847
                ],
                [
                    106.02541077073325,
                    832.0110805955516
                ],
                [
                    102.46197109755508,
                    827.5749405989856
                ],
                [
                    100.23341394936041,
                    820.4014963845907
                ],
                [
                    100.64854415687874,
                    812.8058897069964
                ],
                [
                    103.34149259235025,
                    806.7240844096353
                ],
                [
                    106.5013792930084,
                    800.974834640776
                ],
                [
                    112.16730019072749,
                    796.2239790235599
                ],
                [
                    120.32730180416158,
                    793.3307721276831
                ],
                [
                    126.58296633562387,
                    792.7964191045769
                ],
                [
                    134.51113409401324,
                    795.9751808257337
                ],
                [
                    140.03506036995591,
                    799.3127554894927
                ],
                [
                    147.0039974809053,
                    805.7675398484159
                ],
                [
                    152.60146804564602,
                    818.6487044119449
                ],
                [
                    155.85918224414166,
                    837.646277276787
                ],
                [
                    154.26711174704678,
                    850.396683806419
                ],
                [
                    149.63541293994047,
                    859.1924821302612
                ],
                [
                    142.45203674195164,
                    867.092967748178
                ],
                [
                    134.32572484099316,
                    870.7423477680328
                ],
                [
                    127.50060575254258,
                    870.8982504460807
                ],
                [
                    123.17246168855658,
                    868.4665527347131
                ],
                [
                    118.75447839130229,
                    864.018393359404
                ]
            ],
            "group_id": null,
            "description": "",
            "shape_type": "polygon",
            "flags": {}
        },
        {
            "label": "bean",
            "points": [
                [
                    53.98928687007468,
                    628.4797096949629
                ],
                [
                    46.62540515814055,
                    623.7370922348337
                ],
                [
                    41.464614420417625,
                    617.6553865103792
                ],
                [
                    40.09151326331934,
                    613.4601789474093
                ],
                [
                    39.22651450796874,
                    608.8952685324933
                ],
                [
                    40.178253029887045,
                    604.5319734152727
                ],
                [
                    42.09726369288564,
                    600.4605501607743
                ],
                [
                    45.81654529201951,
                    597.9342866266057
                ],
                [
                    50.397350307576076,
                    596.1847055237397
                ],
                [
                    55.4046255606909,
                    596.2841101301669
                ],
                [
                    59.93185667243995,
                    599.2759678635241
                ],
                [
                    62.65093344822626,
                    599.1449213119022
                ],
                [
                    67.65797552084817,
                    600.7440037689738
                ],
                [
                    70.06792270298209,
                    602.145455637097
                ],
                [
                    73.79902940185713,
                    601.9858089499025
                ],
                [
                    78.20057010888704,
                    603.0177936908609
                ],
                [
                    81.5736145516946,
                    605.4219229900264
                ],
                [
                    85.04405795834649,
                    608.7628528572511
                ],
                [
                    86.52684954001607,
                    613.2621221339656
                ],
                [
                    85.74973408523196,
                    618.5540126769705
                ],
                [
                    84.28989316156597,
                    623.2870106461373
                ],
                [
                    81.81825549530419,
                    626.5489309002324
                ],
                [
                    78.15184825849911,
                    628.8327891501109
                ],
                [
                    73.97339692003263,
                    630.6974779696109
                ],
                [
                    70.62423585720033,
                    631.5269045137492
                ],
                [
                    66.4907754812352,
                    631.5714434843097
                ],
                [
                    61.67458963638819,
                    631.0570898810322
                ],
                [
                    57.92330807695871,
                    630.2717308578922
                ]
            ],
            "group_id": null,
            "description": "",
            "shape_type": "polygon",
            "flags": {}
        },
        {
            "label": "bean",
            "points": [
                [
                    622.6211185597749,
                    1107.0319311698327
                ],
                [
                    623.9011890653079,
                    1120.0547883088088
                ],
                [
                    628.0351459553272,
                    1131.5554131809936
                ],
                [
                    630.4844636212453,
                    1139.9024399365337
                ],
                [
                    629.1591516516243,
                    1143.432890609258
                ],
                [
                    632.9807181002493,
                    1149.849876436066
                ],
                [
                    634.5723965784082,
                    1159.5777337485606
                ],
                [
                    632.6550294607979,
                    1169.3686840916
                ],
                [
                    628.0549647264535,
                    1176.7749570789017
                ],
                [
                    622.9089991884373,
                    1183.6635006086524
                ],
                [
                    614.6905000392511,
                    1188.7950170358265
                ],
                [
                    603.5709168695697,
                    1191.055476361847
                ],
                [
                    595.351896074538,
                    1190.6012335411158
                ],
                [
                    585.6352008389805,
                    1185.0163927078506
                ],
                [
                    579.068876002019,
                    1179.6666091145537
                ],
                [
                    571.1921023310304,
                    1170.002107236787
                ],
                [
                    566.2621757904702,
                    1152.2411138963787
                ],
                [
                    565.4800259838319,
                    1126.96405797515
                ],
                [
                    569.8609218456471,
                    1110.6927663705746
                ],
                [
                    577.4706769507908,
                    1100.1167612032405
                ],
                [
                    588.2309328659918,
                    1091.172253087851
                ],
                [
                    599.443998427461,
                    1087.923293813886
                ],
                [
                    608.3336936266763,
                    1088.973705973552
                ],
                [
                    613.5118632536462,
                    1092.9271809569639
                ],
                [
                    618.4407465025153,
                    1099.5166558015612
                ]
            ],
            "group_id": null,
            "description": "",
            "shape_type": "polygon",
            "flags": {}
        },
        {
            "label": "bean",
            "points": [
                [
                    199.0641934216963,
                    233.87543260259892
                ],
                [
                    213.34627558765567,
                    239.5492231622281
                ],
                [
                    224.27069759456862,
                    248.2737269801583
                ],
                [
                    228.03245772107772,
                    255.0317714791409
                ],
                [
                    231.04003295975187,
                    262.5981965170795
                ],
                [
                    230.8454457829347,
                    270.4321201648822
                ],
                [
                    228.88472229387452,
                    278.09077967863874
                ],
                [
                    223.30441994760858,
                    283.69829016110646
                ],
                [
                    215.97960208652376,
                    288.2601005486611
                ],
                [
                    207.30524131188713,
                    289.78292983665807
                ],
                [
                    198.49950966665924,
                    286.1636456765279
                ],
                [
                    193.85051074920747,
                    287.3091250107357
                ],
                [
                    184.6789085802858,
                    286.24999544298225
                ],
                [
                    180.0548595788211,
                    284.6525112872905
                ],
                [
                    173.66882642669958,
                    286.18960007518444
                ],
                [
                    165.7303588610367,
                    285.90195725605975
                ],
                [
                    159.11150908832914,
                    282.904057342096
                ],
                [
                    152.01370960019773,
                    278.3262901405475
                ],
                [
                    147.9617517409793,
                    271.08187437090726
                ],
                [
                    147.5468413748046,
                    261.70833459405713
                ],
                [
                    148.49561343945672,
                    253.06603040729843
                ],
                [
                    151.67866113306363,
                    246.6140756226041
                ],
                [
                    157.2481530806175,
                    241.44178312056988
                ],
                [
                    163.8404068512915,
                    236.81791731110428
                ],
                [
                    169.34503640657297,
                    234.25693269167095
                ],
                [
                    176.46363364910528,
                    232.781899325688
                ],
                [
                    184.94591332246443,
                    232.0381015497965
                ],
                [
                    191.68034836244175,
                    232.12113120802462
                ]
            ],
            "group_id": null,
            "description": "",
            "shape_type": "polygon",
            "flags": {}
        },
        {
            "label": "bean",
            "points": [
                [
                    731.7368523047074,
                    333.6294910300199
                ],
                [
                    741.5367374690233,
                    340.6427383940692
                ],
                [
                    752.0113119787572,
                    344.7239251660014
                ],
                [
                    759.2796873436218,
                    348.073552615222
                ],
                [
                    760.9229324245676,
                    351.15092573148894
                ],
                [
                    767.685504826082,
                    352.3626776633414
                ],
                [
                    775.3909740849911,
                    357.15453613860194
                ],
                [
                    781.0136093862097,
                    364.4525481435677
                ],
                [
                    783.3580220906297,
                    372.1881509195997
                ],
                [
                    785.0128491192918,
                    379.99306645436076
                ],
                [
                    783.5881325939029,
                    388.8911323174789
                ],
                [
                    778.4158119342912,
                    398.0848199308593
                ],
                [
                    773.1201500664846,
                    403.58900330806506
                ],
                [
                    763.3616395105646,
                    407.028794029286
                ],
                [
                    755.6752003645418,
                    408.3958518892137
                ],
                [
                    744.20473565837,
                    408.0626250028394
                ],
                [
                    728.9096901835771,
                    400.7370383717989
                ],
                [
                    710.9200578925886,
                    385.927215678297
                ],
                [
                    702.2998456371181,
                    372.9588201525926
                ],
                [
                    699.582914325413,
                    361.18046234004896
                ],
                [
                    699.9057907592094,
                    348.1778422876901
                ],
                [
                    704.449786647199,
                    338.3177380076731
                ],
                [
                    710.5650041642052,
                    332.70415693770076
                ],
                [
                    716.4426262298375,
                    331.46486748588546
                ],
                [
                    723.9957810197953,
                    332.0026891451013
                ]
            ],
            "group_id": null,
            "description": "",
            "shape_type": "polygon",
            "flags": {}
        },
        {
            "label": "bean",
            "points": [
                [
                    190.9926185601522,
                    529.6179280972407
                ],
                [
                    194.8293041344375,
                    522.1500284851054
                ],
                [
                    200.104453721127,
                    516.6870613092983
                ],
                [
                    203.92466693351219,
                    515.0193206881851
                ],
                [
                    208.13371381368808,
                    513.808920799341
                ],
                [
                    212.30437152923318,
                    514.360411536977
                ],
                [
                    216.281547729874,
                    515.865313154322
                ],
                [
                    218.95904737959992,
                    519.22798119263
                ],
                [
                    220.97965910158322,
                    523.4827833620204
                ],
                [
                    221.30173752248663,
                    528.3009582836772
                ],
                [
                    218.8715760755006,
                    532.8984690311713
                ],
                [
                    219.2199824675625,
                    535.4994777787357
                ],
                [
                    218.1357042342825,
                    540.4421016845314
                ],
                [
                    217.02135675387976,
                    542.873566781045
                ],
                [
                    217.48051947140618,
                    546.4443381878034
                ],
                [
                    216.8778231777309,
                    550.7581822233927
                ],
                [
                    214.903083172307,
                    554.1981393942708
                ],
                [
                    212.05792755948767,
                    557.809535703086
                ],
                [
                    207.96167511587433,
                    559.607920862309
                ],
                [
                    202.9347010975041,
                    559.3013674214073
                ],
                [
                    198.3752097141683,
                    558.292535951502
                ],
                [
                    195.11131865955136,
                    556.1894928382637
                ],
                [
                    192.66552221624463,
                    552.857463174269
                ],
                [
                    190.57033774921368,
                    548.9987249885215
                ],
                [
                    189.514760544422,
                    545.8505255704056
                ],
                [
                    189.1301705719432,
                    541.8836901800041
                ],
                [
                    189.21306323449886,
                    537.2145767605991
                ],
                [
                    189.63841542893817,
                    533.5458643747011
                ]
            ],
            "group_id": null,
            "description": "",
            "shape_type": "polygon",
            "flags": {}
        },
        {
            "label": "bean",
            "points": [
                [
                    933.5881430079705,
                    772.5103535444442
                ],
                [
                    933.8326976553594,
                    762.1085077708311
                ],
                [
                    931.6738718678889,
                    752.6297330354553
                ],
                [
                    930.5427299332531,
                    745.8038623715479
                ],
                [
                    931.9312965559665,
                    743.1469837666069
                ],
                [
                    929.5289116336921,
                    737.710443913485
                ],
                [
                    929.2091277673416,
                    729.8784888757915
                ],
                [
                    931.6699375661598,
                    722.3388178726035
                ],
                [
                    936.0217672051449,
                    716.9425471404775
                ],
                [
                    940.7552660067664,
                    712.0080618341226
                ],
                [
                    947.7485837705026,
                    708.7596657198359
                ],
                [
                    956.7586591178422,
                    708.0597882341922
                ],
                [
                    963.2133784492162,
                    709.2194758653546
                ],
                [
                    970.3571785251812,
                    714.5740020095374
                ],
                [
                    975.0327502065513,
                    719.4359221138128
                ],
                [
                    980.3280987404498,
                    727.8305732999357
                ],
                [
                    982.5121668530049,
                    742.3273464905208
                ],
                [
                    980.6914225431804,
                    762.3511221234164
                ],
                [
                    975.6574329990884,
                    774.7646368312969
                ],
                [
                    968.6200536683743,
                    782.3689239696197
                ],
                [
                    959.2490955511561,
                    788.378584131673
                ],
                [
                    950.0697186496947,
                    789.8494288380926
                ],
                [
                    943.142244358279,
                    788.1538911391647
                ],
                [
                    939.4295085700078,
                    784.5291980282134
                ],
                [
                    936.1682435927282,
                    778.8485923285266
                ]
            ],
            "group_id": null,
            "description": "",
            "shape_type": "polygon",
            "flags": {}
        },
        {
            "label": "bean",
            "points": [
                [
                    194.09659863662807,
                    789.8190470463244
                ],
                [
                    189.4795702336746,
                    798.7323465833889
                ],
                [
                    183.1315088666415,
                    805.2526622448362
                ],
                [
                    178.53430313648306,
                    807.2431913732617
                ],
                [
                    173.46917892474596,
                    808.6878622083336
                ],
                [
                    168.4502518433273,
                    808.0296313279292
                ],
                [
                    163.66415844933576,
                    806.2334584298078
                ],
                [
                    160.44208259966558,
                    802.2199514163436
                ],
                [
                    158.0104990020247,
                    797.1416391496517
                ],
                [
                    157.6229131056833,
                    791.3909142431581
                ],
                [
                    160.54734467748003,
                    785.9035627058264
                ],
                [
                    160.1280759683886,
                    782.7991329103464
                ],
                [
                    161.4328853677594,
                    776.899872119558
                ],
                [
                    162.77387979332883,
                    773.997800875332
                ],
                [
                    162.22132804850892,
                    769.7359124221043
                ],
                [
                    162.94660663920286,
                    764.5871308312396
                ],
                [
                    165.32298867962825,
                    760.481375498256
                ],
                [
                    168.74682001030914,
                    756.1709992587025
                ],
                [
                    173.67620854414892,
                    754.0245395525332
                ],
                [
                    179.72561795608596,
                    754.3904259174802
                ],
                [
                    185.2124635190833,
                    755.5945150912382
                ],
                [
                    189.1401968220969,
                    758.1045988070388
                ],
                [
                    192.08344338946603,
                    762.0815374382582
                ],
                [
                    194.60476707013038,
                    766.6871281760858
                ],
                [
                    195.8750379436933,
                    770.4446565138372
                ],
                [
                    196.33784960548977,
                    775.1792664959291
                ],
                [
                    196.23809741834654,
                    780.752079286832
                ],
                [
                    195.7262329131738,
                    785.1308650377425
                ]
            ],
            "group_id": null,
            "description": "",
            "shape_type": "polygon",
            "flags": {}
        },
        {
            "label": "bean",
            "points": [
                [
                    974.4314105246169,
                    873.6193246163596
                ],
                [
                    981.1251259508015,
                    878.1163845036596
                ],
                [
                    985.772473805631,
                    883.813458741783
                ],
                [
                    986.9680633492633,
                    887.7077301338614
                ],
                [
                    987.6907297969457,
                    891.9349389211721
                ],
                [
                    986.7466244140024,
                    895.9464827996167
                ],
                [
                    984.9180206714948,
                    899.6728948341739
                ],
                [
                    981.4591056359714,
                    901.943904161658
                ],
                [
                    977.2205928389883,
                    903.48405454765
                ],
                [
                    972.6194089633632,
                    903.3107634782432
                ],
                [
                    968.5053971361739,
                    900.4757401750287
                ],
                [
                    966.0039015354347,
                    900.5524057499858
                ],
                [
                    961.4267345500567,
                    898.9950113004444
                ],
                [
                    959.2337189199504,
                    897.6623127916229
                ],
                [
                    955.8014964842757,
                    897.7488928624592
                ],
                [
                    951.771914479024,
                    896.7247545092514
                ],
                [
                    948.7095198463176,
                    894.4509638619573
                ],
                [
                    945.5724633294349,
                    891.3109797230975
                ],
                [
                    944.2808707209806,
                    887.1342923430748
                ],
                [
                    945.0791984496511,
                    882.2628701489754
                ],
                [
                    946.4962269285442,
                    877.9183888752987
                ],
                [
                    948.8199653521256,
                    874.9480964858774
                ],
                [
                    952.2264300885967,
                    872.8999507071958
                ],
                [
                    956.0969203877347,
                    871.2470106188312
                ],
                [
                    959.1886833298913,
                    870.5360461329644
                ],
                [
                    962.9889282634111,
                    870.5622557645007
                ],
                [
                    967.4078739471537,
                    871.1154063164597
                ],
                [
                    970.8436424969083,
                    871.9013349131003
                ]
            ],
            "group_id": null,
            "description": "",
            "shape_type": "polygon",
            "flags": {}
        },
        {
            "label": "bean",
            "points": [
                [
                    102.72688903382821,
                    932.2536529220041
                ],
                [
                    92.4468338592869,
                    932.3435959942334
                ],
                [
                    83.49281156796809,
                    929.7021744375907
                ],
                [
                    79.47570209184981,
                    926.4722998847169
                ],
                [
                    75.72580704365272,
                    922.5528004008943
                ],
                [
                    73.89777409502162,
                    917.6614672598471
                ],
                [
                    73.21003847495986,
                    912.433655202678
                ],
                [
                    75.28017839899498,
                    907.5620887115797
                ],
                [
                    78.69373042366956,
                    902.897524764476
                ],
                [
                    83.70130630762127,
                    899.7715319167347
                ],
                [
                    90.06967350962945,
                    899.7909087858549
                ],
                [
                    92.67154299415697,
                    897.911979657469
                ],
                [
                    98.6302048085415,
                    896.2567201717831
                ],
                [
                    101.89895485223036,
                    896.0795624931263
                ],
                [
                    105.4820280363412,
                    893.5210866491807
                ],
                [
                    110.48304050739281,
                    891.6995272618846
                ],
                [
                    115.33886272339197,
                    891.8855938134436
                ],
                [
                    120.88511985480287,
                    892.9275851975617
                ],
                [
                    125.20342564554295,
                    896.3850085060367
                ],
                [
                    127.79294485240368,
                    902.0745069577245
                ],
                [
                    129.3537633731136,
                    907.6554650297205
                ],
                [
                    128.98229226380732,
                    912.4452364552212
                ],
                [
                    126.81059495373717,
                    917.0450622162613
                ],
                [
                    123.86737212905388,
                    921.5634826925326
                ],
                [
                    121.08633050277334,
                    924.5328640732237
                ],
                [
                    117.03292811867118,
                    927.2374833880017
                ],
                [
                    111.95082504841821,
                    929.833562323088
                ],
                [
                    107.7483682917135,
                    931.4783538125563
                ]
            ],
            "group_id": null,
            "description": "",
            "shape_type": "polygon",
            "flags": {}
        },
        {
            "label": "bean",
            "points": [
                [
                    665.2207481320088,
                    868.1479918776133
                ],
                [
                    654.4027601014188,
                    865.5484298641487
                ],
                [
                    645.6894907264806,
                    860.436873232661
                ],
                [
                    642.3136721139339,
                    856.0029049815893
                ],
                [
                    639.3982908877574,
                    850.9169890016245
                ],
                [
                    638.7544016116262,
                    845.3172553647775
                ],
                [
                    639.3956286788289,
                    839.6640592048429
                ],
                [
                    642.839845448207,
                    835.1064727846575
                ],
                [
                    647.6407218138226,
                    831.1176164677009
                ],
                [
                    653.7141467977634,
                    829.157175522215
                ],
                [
                    660.3961723185272,
                    830.8461894012097
                ],
                [
                    663.6182682488322,
                    829.5609202973745
                ],
                [
                    670.3068190756719,
                    829.3894039794862
                ],
                [
                    673.7853588100717,
                    830.0604613700832
                ],
                [
                    678.2149854118745,
                    828.3208848145191
                ],
                [
                    683.9413303077329,
                    827.7243328397257
                ],
                [
                    688.9916422842236,
                    829.1915157132925
                ],
                [
                    694.5437228053255,
                    831.7356819726574
                ],
                [
                    698.1764681091104,
                    836.4867942189533
                ],
                [
                    699.4117964395538,
                    843.1216607748898
                ],
                [
                    699.5952483293147,
                    849.37334214063
                ],
                [
                    697.9560437046789,
                    854.2904063305012
                ],
                [
                    694.4760553088489,
                    858.5368964375284
                ],
                [
                    690.2071595825071,
                    862.4959976519083
                ],
                [
                    686.5125414279668,
                    864.8759098799866
                ],
                [
                    681.5509341868901,
                    866.6452415381274
                ],
                [
                    675.5374505051311,
                    868.0313880060716
                ],
                [
                    670.6957258684182,
                    868.6521307091289
                ]
            ],
            "group_id": null,
            "description": "",
            "shape_type": "polygon",
            "flags": {}
        },
        {
            "label": "bean",
            "points": [
                [
                    888.1378149101938,
                    948.7453803741427
                ],
                [
                    875.579707702522,
                    951.3171673703255
                ],
                [
                    863.9970652068089,
                    950.2199760512025
                ],
                [
                    858.3161588275436,
                    947.2186541718017
                ],
                [
                    852.7988367606735,
                    943.3071580944504
                ],
                [
                    849.4029793741793,
                    937.7430245347743
                ],
                [
                    847.3227474309094,
                    931.4929907377307
                ],
                [
                    848.7016594613328,
                    925.0197453862376
                ],
                [
                    851.7735144223687,
                    918.4788368595631
                ],
                [
                    857.1604785701095,
                    913.4441393366764
                ],
                [
                    864.9578638671162,
                    911.943093778733
                ],
                [
                    867.69650904095,
                    909.0146005203578
                ],
                [
                    874.5957637194496,
                    905.5568178100169
                ],
                [
                    878.5536669741689,
                    904.5567801805358
                ],
                [
                    882.3319732288119,
                    900.5595237113647
                ],
                [
                    888.0199761702665,
                    897.1269818909501
                ],
                [
                    894.005997324229,
                    896.1926292092069
                ],
                [
                    901.0396859028415,
                    896.1432098354879
                ],
                [
                    907.1430728694584,
                    899.351624280143
                ],
                [
                    911.6598557930707,
                    905.7128059437564
                ],
                [
                    914.8921288671697,
                    912.1871137013832
                ],
                [
                    915.5724503297006,
                    918.1532698572599
                ],
                [
                    914.004879555583,
                    924.31739667766
                ],
                [
                    911.4739263943304,
                    930.56636806857
                ],
                [
                    908.7744031580481,
                    934.8757837024114
                ],
                [
                    904.4551951036217,
                    939.1649773073469
                ],
                [
                    898.851477199682,
                    943.5672970062958
                ],
                [
                    894.0987616328574,
                    946.5917349633555
                ]
            ],
            "group_id": null,
            "description": "",
            "shape_type": "polygon",
            "flags": {}
        },
        {
            "label": "bean",
            "points": [
                [
                    371.2596576089876,
                    96.5720210619584
                ],
                [
                    373.2809176301263,
                    101.99229268111851
                ],
                [
                    376.34439603342594,
                    106.43282650967834
                ],
                [
                    378.3332683223821,
                    109.71922906546502
                ],
                [
                    378.16937512954263,
                    111.38138846952378
                ],
                [
                    380.52355596283036,
                    113.68446266193138
                ],
                [
                    382.3039063940772,
                    117.66007296467515
                ],
                [
                    382.59774142203224,
                    122.06708886992499
                ],
                [
                    381.4793060034098,
                    125.76374860360399
                ],
                [
                    380.0698069971703,
                    129.30197492658516
                ],
                [
                    377.15325488175824,
                    132.44312132661236
                ],
                [
                    372.67633331272515,
                    134.69113415903732
                ],
                [
                    369.1263097573773,
                    135.44419992401882
                ],
                [
                    364.3571343337508,
                    134.17633762637735
                ],
                [
                    360.95560069183193,
                    132.64587984320505
                ],
                [
                    356.5071051476673,
                    129.42173752508285
                ],
                [
                    352.39508366876026,
                    122.39637838638969
                ],
                [
                    349.1965290038749,
                    111.67954786715626
                ],
                [
                    349.21665825554993,
                    104.21798978487726
                ],
                [
                    351.2568572613874,
                    98.81926160238979
                ],
                [
                    354.8230659089164,
                    93.75495809313291
                ],
                [
                    359.227714600982,
                    91.07354686578304
                ],
                [
                    363.13080576797415,
                    90.49807014369426
                ],
                [
                    365.7831566950961,
                    91.59153895916289
                ],
                [
                    368.62823529413157,
                    93.8407368277646
                ]
            ],
            "group_id": null,
            "description": "",
            "shape_type": "polygon",
            "flags": {}
        },
        {
            "label": "bean",
            "points": [
                [
                    364.4785130464303,
                    673.7934738700659
                ],
                [
                    364.5693357628713,
                    684.2492113076804
                ],
                [
                    361.90208107505896,
                    693.3562544605645
                ],
                [
                    358.64061831439767,
                    697.4420148215073
                ],
                [
                    354.6827860835624,
                    701.2559941608067
                ],
                [
                    349.74361565190594,
                    703.1152675026007
                ],
                [
                    344.46467553671715,
                    703.8147562648467
                ],
                [
                    339.5454650730582,
                    701.7092384308143
                ],
                [
                    334.8352816404955,
                    698.237350090368
                ],
                [
                    331.6787165491578,
                    693.1441966245
                ],
                [
                    331.6982829242658,
                    686.6669964305346
                ],
                [
                    329.80097784884134,
                    684.0206619785042
                ],
                [
                    328.12952990762244,
                    677.9601688826076
                ],
                [
                    327.9506396249673,
                    674.6355571343514
                ],
                [
                    325.3671418598124,
                    670.9912505818342
                ],
                [
                    323.527767602161,
                    665.9047726951155
                ],
                [
                    323.7156538865911,
                    660.9659663101111
                ],
                [
                    324.76783595762765,
                    655.3249257375719
                ],
                [
                    328.2590729031618,
                    650.9328217306668
                ],
                [
                    334.0042147107621,
                    648.2990486178874
                ],
                [
                    339.6397546125925,
                    646.7115562977368
                ],
                [
                    344.4763700540345,
                    647.0893757081019
                ],
                [
                    349.1211821603792,
                    649.2981865055673
                ],
                [
                    353.6837928373964,
                    652.2917078975044
                ],
                [
                    356.6822147998556,
                    655.1202764755677
                ],
                [
                    359.41328532055593,
                    659.2429499765943
                ],
                [
                    362.03475393548644,
                    664.4119042702498
                ],
                [
                    363.6956315033722,
                    668.6861794268511
                ]
            ],
            "group_id": null,
            "description": "",
            "shape_type": "polygon",
            "flags": {}
        },
        {
            "label": "bean",
            "points": [
                [
                    421.4400309364152,
                    97.1224052775723
                ],
                [
                    429.86999945324976,
                    98.83267114393803
                ],
                [
                    437.89506196999355,
                    98.42446256381821
                ],
                [
                    443.613064046668,
                    98.48019319303634
                ],
                [
                    445.5751989861555,
                    100.01208228938425
                ],
                [
                    450.34571372361626,
                    98.81660641858181
                ],
                [
                    456.7655756859204,
                    99.68821454838047
                ],
                [
                    462.5469130790157,
                    102.81355334420583
                ],
                [
                    466.3114342837567,
                    107.18962357459242
                ],
                [
                    469.64515120856584,
                    111.81390107353411
                ],
                [
                    471.2810791657614,
                    118.05976341639183
                ],
                [
                    470.55238074483606,
                    125.60144260032448
                ],
                [
                    468.67853914615597,
                    130.76335492501573
                ],
                [
                    463.29157317468827,
                    135.88601181710465
                ],
                [
                    458.66114833771707,
                    139.041925678865
                ],
                [
                    451.06641997317786,
                    142.19736447516598
                ],
                [
                    438.9539840863131,
                    141.89878148584484
                ],
                [
                    422.92063313738527,
                    137.49172571826372
                ],
                [
                    413.5436474090643,
                    131.53481586714113
                ],
                [
                    408.3691669269673,
                    124.62094232198547
                ],
                [
                    404.8286699683358,
                    116.01131325104282
                ],
                [
                    404.954336422902,
                    108.21803674614003
                ],
                [
                    407.33238206867065,
                    102.74344156280847
                ],
                [
                    410.8171936001598,
                    100.203198326543
                ],
                [
                    415.9100903752733,
                    98.33388127953121
                ]
            ],
            "group_id": null,
            "description": "",
            "shape_type": "polygon",
            "flags": {}
        },
        {
            "label": "bean",
            "points": [
                [
                    570.3515139596441,
                    693.9816362785343
                ],
                [
                    571.7552129027534,
                    706.1276802590598
                ],
                [
                    575.7942929638184,
                    716.8047038229589
                ],
                [
                    578.2121884938418,
                    724.5630110331874
                ],
                [
                    577.0340078095405,
                    727.8831984994575
                ],
                [
                    580.6997124877278,
                    733.8157852341451
                ],
                [
                    582.3405652494052,
                    742.8782513804092
                ],
                [
                    580.7117923098245,
                    752.0572367317759
                ],
                [
                    576.5440174614234,
                    759.0522710250572
                ],
                [
                    571.8590572572958,
                    765.5725555306913
                ],
                [
                    564.2818938860087,
                    770.5016884946197
                ],
                [
                    553.9543137448002,
                    772.796036663288
                ],
                [
                    546.2863359973068,
                    772.506493184901
                ],
                [
                    537.1394660099126,
                    767.4480866522869
                ],
                [
                    530.9327358472943,
                    762.5576026475237
                ],
                [
                    523.4348129240194,
                    753.657447109134
                ],
                [
                    518.5526028880641,
                    737.1445213615241
                ],
                [
                    517.4148320844058,
                    713.5414072932862
                ],
                [
                    521.2349705073966,
                    698.2675245993574
                ],
                [
                    528.1567033830374,
                    688.261680972319
                ],
                [
                    538.0412796775057,
                    679.7284289837103
                ],
                [
                    548.4400059642848,
                    676.5090074647636
                ],
                [
                    556.7427341889833,
                    677.3445387076719
                ],
                [
                    561.6330385273803,
                    680.9532493032422
                ],
                [
                    566.3336198109229,
                    687.0288221662215
                ]
            ],
            "group_id": null,
            "description": "",
            "shape_type": "polygon",
            "flags": {}
        },
        {
            "label": "bean",
            "points": [
                [
                    1081.863848284579,
                    572.7606823205807
                ],
                [
                    1090.338382701034,
                    586.1604925426049
                ],
                [
                    1094.1947355176565,
                    600.0506237615218
                ],
                [
                    1093.274560598624,
                    607.9504253735299
                ],
                [
                    1091.243320508554,
                    616.0626057683317
                ],
                [
                    1086.38997576171,
                    622.4487853052609
                ],
                [
                    1080.1734333604945,
                    627.6149734700875
                ],
                [
                    1072.1763887960808,
                    628.8760270201592
                ],
                [
                    1063.3554071047226,
                    628.2075136940249
                ],
                [
                    1055.2325605206706,
                    624.1946888657079
                ],
                [
                    1050.0800212825625,
                    615.832409288086
                ],
                [
                    1045.5293793596722,
                    613.9551866964956
                ],
                [
                    1038.5394701721323,
                    607.4960357017001
                ],
                [
                    1035.6522772829915,
                    603.3564903930018
                ],
                [
                    1029.4231399905482,
                    600.7476603861584
                ],
                [
                    1022.9962865564287,
                    595.6792850661465
                ],
                [
                    1019.2895309854384,
                    589.1633834045051
                ],
                [
                    1016.1307848320652,
                    581.0443272852866
                ],
                [
                    1017.1010016476605,
                    572.5641399917433
                ],
                [
                    1022.3697279028122,
                    564.528805134894
                ],
                [
                    1028.3341378206937,
                    557.9302468151711
                ],
                [
                    1034.8441057116165,
                    554.5096220771799
                ],
                [
                    1042.5715200123166,
                    553.6033562791598
                ],
                [
                    1050.8206970600643,
                    553.7746728839844
                ],
                [
                    1056.930329778483,
                    554.9971335982741
                ],
                [
                    1063.7312717145367,
                    558.1031603264272
                ],
                [
                    1071.2278973133205,
                    562.6459635917066
                ],
                [
                    1076.7763972788377,
                    566.8119471937846
                ]
            ],
            "group_id": null,
            "description": "",
            "shape_type": "polygon",
            "flags": {}
        },
        {
            "label": "reference",
            "points": [
                [
                    314.8780015939384,
                    799.7699790124633
                ],
                [
                    313.5174299522346,
                    791.0747897059352
                ],
                [
                    314.3825952678838,
                    779.3982803964876
                ],
                [
                    317.40704507826126,
                    769.3414229836744
                ],
                [
                    323.32303977376665,
                    758.4296519571551
                ],
                [
                    333.17836191290246,
                    747.6155632221031
                ],
                [
                    346.78014518443524,
                    740.4529215108046
                ],
                [
                    362.6039074215816,
                    736.2426787771194
                ],
                [
                    376.26360226542226,
                    737.9647901220231
                ],
                [
                    389.1593478478079,
                    742.034522435008
                ],
                [
                    401.41687474612183,
                    750.5779408798012
                ],
                [
                    408.6549195000223,
                    759.0229945821557
                ],
                [
                    413.1298830310795,
                    766.1335950761018
                ],
                [
                    415.9829063328986,
                    775.9403168847414
                ],
                [
                    418.738471572263,
                    789.1422080542148
                ],
                [
                    415.487075130308,
                    806.4018886446672
                ],
                [
                    408.204017716458,
                    818.8676213310328
                ],
                [
                    399.01655331877316,
                    828.5715424659169
                ],
                [
                    388.71929516292585,
                    834.9112626181886
                ],
                [
                    375.49479845973485,
                    839.9290938895856
                ],
                [
                    359.4242631302075,
                    840.8582062516766
                ],
                [
                    343.06623134808507,
                    835.897814789962
                ],
                [
                    332.999336179942,
                    829.6404217822924
                ],
                [
                    323.28409331392186,
                    819.9245577554021
                ],
                [
                    317.79440263786825,
                    809.8305899056213
                ]
            ],
            "group_id": null,
            "description": "",
            "shape_type": "polygon",
            "flags": {}
        }
    ],
    "imagePath": "bean_synthetic_49_skhj.jpg",
    "imageData": null,
    "imageHeight": 1221,
    "imageWidth": 1232
}